simple_neural_net/__init__.py
simple_neural_net/activation_models.py
simple_neural_net/core.py
simple_neural_net/cost_models.py
simple_neural_net/layers.py
simple_neural_net/prediction_models.py
simple_neural_net-0.1.0.dist-info/LICENSE
simple_neural_net-0.1.0.dist-info/METADATA
simple_neural_net-0.1.0.dist-info/WHEEL
simple_neural_net-0.1.0.dist-info/top_level.txt
simple_neural_net-0.1.0.dist-info/RECORD
